{
  "title": "建設業界全体で土木技術を開発・共有、新フォーラムが26年秋に発足",
  "url": "https://xtech.nikkei.com/atcl/nxt/column/18/00142/02700/",
  "section": "技術・トレンド",
  "date": "2026-07-06",
  "is_in_scope": true,
  "maturity": "確定",
  "lead": "建設業界全体で土木分野の技術開発を共同で推進する新組織「建設技術共創・実装フォーラム（仮称）」が、2026年秋に発足します。",
  "bullets": [
    "フォーラムは「先端建設技術センター」が設立し、建設会社や建設コンサルタント会社、研究機関などが入会対象です。",
    "2026年秋に立ち上がり、土木分野の技術開発を共同で推進し、業界全体で新技術を共有できる体制を整えます。"
  ],
  "tags": [
    "#DX",
    "#政策",
    "#継続ウォッチ"
  ],
  "source_name": "自動取得"
}