{
  "title": "九州整備局／五ケ瀬高千穂道路新津花トンネル／２６年度に着工",
  "url": "https://www.decn.co.jp/?p=183954",
  "section": "国交省・規制・政策",
  "date": "2026-04-30",
  "is_in_scope": true,
  "maturity": "確定",
  "lead": "九州地方整備局は、九州中央自動車道の一部である「国道218号五ケ瀬高千穂道路」の最長トンネル「新津花トンネル」（延長2433m）の工事に2026年度着手すると発表しました。工区分けして発注される予定で、詳細は今後の発注見通しで公表されます。",
  "bullets": [
    "2026年度は事業費36億3000万円が配分され、新津花トンネル工事のほか調査設計や葛原地区の用地買収が進められます。",
    "新津花トンネルはトンネル等級Aであり、本坑に並行して避難坑（延長2440メートル）も設置される計画です。",
    "五ケ瀬高千穂道路の全体事業費は559億円、用地進捗率は約73%、事業費ベース進捗率は約35%で、災害対応や地域振興への寄与が期待されます。"
  ],
  "tags": [
    "#地方整備局",
    "#発注",
    "#政策",
    "#継続ウォッチ"
  ],
  "source_name": "自動取得"
}