{
  "title": "建機の自動運転、海外勢を「逆転する一手」　コマツとティアフォー",
  "url": "https://xtech.nikkei.com/atcl/nxt/column/18/00142/02645/",
  "section": "技術・トレンド",
  "date": "2026-05-25",
  "is_in_scope": true,
  "maturity": "提言",
  "lead": "建設機械の自動運転技術の開発が世界で加速しており、国内ではコマツとティアフォーが2027年度内の土木・砕石現場向け自動運転ダンプトラックの実用化を目指しています。(本文未取得のため見出しとリードのみ)",
  "bullets": [
    "コマツは自動運転ソフトウエア「Autoware」開発のティアフォー、子会社EARTHBRAINと協業し、2027年度内に土木・砕石現場向け自動運転ダンプトラックの実用化を目指しています。",
    "米国ではデータセンター建設ラッシュ、日本でも建設業の人手不足が深刻化しており、建機の自動運転は現実的な解決策としてニーズが高まっています。",
    "ダンプトラックの世界市場の約10%を占める土木・砕石用途を含め、大部分が将来的に自動運転に置き換わるとコマツは見ています。"
  ],
  "tags": [
    "#DX",
    "#自動運転",
    "#継続ウォッチ"
  ],
  "source_name": "自動取得"
}