{
  "title": "過去最多の「物価高倒産」、建設業が3割占める 帝国データバンク調査",
  "url": "https://xtech.nikkei.com/atcl/nxt/column/18/00142/02634/",
  "section": "資材価格・コスト",
  "date": "2026-05-20",
  "is_in_scope": true,
  "maturity": "確定",
  "lead": "帝国データバンクの調査によると、2026年4月の物価高を原因とする倒産が過去最多の108件を記録し、そのうち建設業が30.6％を占める33件で最も多くなりました。",
  "bullets": [
    "2026年4月に発生した物価高を原因とする倒産は、単月で過去最多となる108件に上りました。",
    "業種別では建設業が33件で全体の30.6％を占め、最も高い割合となりました。",
    "記事本文は有料会員限定のため、詳細な分析や今後の見通しは不明です（本文未取得のため見出しとリードのみ）。"
  ],
  "tags": [
    "#資材価格",
    "#継続ウォッチ"
  ],
  "source_name": "自動取得"
}